sourceserver/__init__.py
sourceserver/exceptions.py
sourceserver/masterserver.py
sourceserver/peekablestream.py
sourceserver/sourceserver.py
sourceserver-0.10.0.dist-info/LICENSE
sourceserver-0.10.0.dist-info/METADATA
sourceserver-0.10.0.dist-info/WHEEL
sourceserver-0.10.0.dist-info/top_level.txt
sourceserver-0.10.0.dist-info/RECORD
