Metadata-Version: 2.1
Name: sourceserver
Version: 0.10.0
Summary: Query Source engine servers over UDP
Home-page: https://github.com/Derpius/pythonsourceserver/
Author: Derpius
Author-email: derpius.yt@gmail.com
Classifier: Programming Language :: Python :: 3.8
Classifier: License :: OSI Approved :: GNU General Public License v3 (GPLv3)
License-File: LICENSE
